[
  {
    "date": "27.09.2020",
    "team_home": [
      "Ad Astra Sarnen"
    ],
    "team_away": [
      "Ticino Unihockey"
    ]
  },
  {
    "date": "27.09.2020",
    "team_home": [
      "Unihockey Limmattal"
    ],
    "team_away": [
      "Ticino Unihockey"
    ]
  },
  {
    "date": "25.10.2020",
    "team_home": [
      "Ticino Unihockey"
    ],
    "team_away": [
      "SU Mendrisiotto"
    ]
  },
  {
    "date": "25.10.2020",
    "team_home": [
      "Ticino Unihockey"
    ],
    "team_away": [
      "Vipers InnerSchwyz"
    ]
  },
  {
    "date": "15.11.2020",
    "team_home": [
      "Floorball Albis"
    ],
    "team_away": [
      "Ticino Unihockey"
    ]
  },
  {
    "date": "15.11.2020",
    "team_home": [
      "ESV Eschenbach"
    ],
    "team_away": [
      "Ticino Unihockey"
    ]
  },
  {
    "date": "06.12.2020",
    "team_home": [
      "UHC Astros Rotkreuz"
    ],
    "team_away": [
      "Ticino Unihockey"
    ]
  },
  {
    "date": "06.12.2020",
    "team_home": [
      "Ticino Unihockey"
    ],
    "team_away": [
      "Ad Astra Sarnen"
    ]
  },
  {
    "date": "24.01.2021",
    "team_home": [
      "Vipers InnerSchwyz"
    ],
    "team_away": [
      "Ticino Unihockey"
    ]
  },
  {
    "date": "24.01.2021",
    "team_home": [
      "Ticino Unihockey"
    ],
    "team_away": [
      "Unihockey Limmattal"
    ]
  },
  {
    "date": "21.02.2021",
    "team_home": [
      "SU Mendrisiotto"
    ],
    "team_away": [
      "Ticino Unihockey"
    ]
  },
  {
    "date": "21.02.2021",
    "team_home": [
      "Ticino Unihockey"
    ],
    "team_away": [
      "Floorball Albis"
    ]
  },
  {
    "date": "21.03.2021",
    "team_home": [
      "Ticino Unihockey"
    ],
    "team_away": [
      "ESV Eschenbach"
    ]
  },
  {
    "date": "21.03.2021",
    "team_home": [
      "Ticino Unihockey"
    ],
    "team_away": [
      "UHC Astros Rotkreuz"
    ]
  }
]